mindful_agents/__init__.py
mindful_agents/api.py
mindful_agents/data.py
mindful_agents/templates/index.py
mindful_agents-25.3.2.dist-info/licenses/LICENSE
mindful_agents-25.3.2.dist-info/METADATA
mindful_agents-25.3.2.dist-info/WHEEL
mindful_agents-25.3.2.dist-info/top_level.txt
mindful_agents-25.3.2.dist-info/RECORD
