Metadata-Version: 2.4
Name: mindful-agents
Version: 25.3.2
Summary: A powerful toolkit for interacting with large language models featuring vision capabilities and customizable agents.
Author-email: ikmalsaid <ikmalsaid@gmail.com>
Project-URL: Homepage, https://github.com/ikmalsaid/mindful-agents
Project-URL: Issues, https://github.com/ikmalsaid/mindful-agents/issues
Keywords: mindful-agents,mindful_agents
Classifier: Programming Language :: Python :: 3
Classifier: Topic :: Scientific/Engineering :: Artificial Intelligence
Classifier: License :: OSI Approved :: GNU Affero General Public License v3
Classifier: Operating System :: OS Independent
Requires-Python: >=3.8
License-File: LICENSE
Requires-Dist: colorpaws
Requires-Dist: flask
Dynamic: license-file
